odata1cw/__init__.py
odata1cw/catalog.py
odata1cw/core.py
odata1cw/document.py
odata1cw/informationregister.py
odata1cw/postingmode.py
odata1cw/utils.py
odata1cw-0.0.4.dist-info/LICENSE
odata1cw-0.0.4.dist-info/METADATA
odata1cw-0.0.4.dist-info/WHEEL
odata1cw-0.0.4.dist-info/top_level.txt
odata1cw-0.0.4.dist-info/RECORD
